StorageTopology/StorageTopology.py
StorageTopology/__init__.py
StorageTopology-1.7.dist-info/METADATA
StorageTopology-1.7.dist-info/WHEEL
StorageTopology-1.7.dist-info/top_level.txt
StorageTopology-1.7.dist-info/RECORD
