Metadata-Version: 2.1
Name: StorageTopology
Version: 1.7
Summary: A scientific computation library for performance analysis of erasure coding and/or replication in a distributed data storage environment.
Home-page: https://github.com/whatsacomputertho/StorageTopology
Author: Ethan Balcik
Author-email: emb71@psu.edu
License: UNKNOWN
Project-URL: Bug Tracker, https://github.com/whatsacomputertho/StorageTopology/issues
Platform: UNKNOWN
Classifier: Programming Language :: Python :: 3
Classifier: License :: OSI Approved :: MIT License
Classifier: Operating System :: OS Independent
Requires-Python: >=3.6
Requires-Dist: numpy
Requires-Dist: sympy
Requires-Dist: grinpy
Requires-Dist: networkx
